{
  "id": "10_A1_fragen_stellen",
  "title_de": "Wer? Was? Wann? Wo?",
  "title_fa": "چطور سؤال بپرسیم؟",

  "vocabulary_before_lesson": [
    { "de": "Frage", "fa": "سؤال" },
    { "de": "Antwort", "fa": "جواب" },
    { "de": "wer", "fa": "چه کسی" },
    { "de": "was", "fa": "چه / چی" },
    { "de": "wann", "fa": "کی" },
    { "de": "wo", "fa": "کجا (مکان ثابت)" },
    { "de": "woher", "fa": "از کجا" },
    { "de": "wie", "fa": "چطور / چگونه" },
    { "de": "wie viel", "fa": "چقدر (غیرقابل شمارش)" },
    { "de": "wie viele", "fa": "چند تا (قابل شمارش)" },
    { "de": "ja", "fa": "بله" },
    { "de": "nein", "fa": "نه" }
  ],

  "pages": [
    {
      "page": 1,
      "title_fa": "چرا سؤال پرسیدن مهم است؟",
      "explanation_fa": "اگر سؤال نپرسیم، نمی‌توانیم اطلاعات بگیریم. در آلمانی، سؤال پرسیدن قانون مشخصی دارد. وقتی این قانون را بفهمی، خیلی راحت می‌توانی با آلمانی‌زبان‌ها ارتباط بگیری."
    },
    {
      "page": 2,
      "title_fa": "سؤال‌های بله / نه (Ja / Nein)",
      "explanation_fa": "ساده‌ترین نوع سؤال در آلمانی این است که جوابش فقط «بله» یا «نه» باشد. در این نوع سؤال، فعل همیشه اول جمله می‌آید.",
      "examples": [
        {
          "audio_de": "A1_10_01",
          "de": "Kommst du aus Deutschland?",
          "fa": "آیا تو اهل آلمان هستی؟"
        },
        {
          "audio_de": "A1_10_02",
          "de": "Arbeitest du hier?",
          "fa": "آیا اینجا کار می‌کنی؟"
        }
      ]
    },
    {
      "page": 3,
      "title_fa": "قاعده خیلی مهم جای فعل",
      "explanation_fa": "در جمله خبری، فعل جای دوم است. اما در سؤال بله/نه، فعل به جای اول می‌آید. این مهم‌ترین قانون این درس است."
    },
    {
      "page": 4,
      "title_fa": "سؤال با کلمه پرسشی (W-Fragen)",
      "explanation_fa": "اگر جواب فقط بله یا نه نباشد، از کلمات پرسشی استفاده می‌کنیم. این سؤال‌ها اطلاعات دقیق می‌خواهند.",
      "examples": [
        {
          "audio_de": "A1_10_03",
          "de": "Wo wohnst du?",
          "fa": "کجا زندگی می‌کنی؟"
        },
        {
          "audio_de": "A1_10_04",
          "de": "Was machst du?",
          "fa": "چه کار می‌کنی؟"
        }
      ]
    },
    {
      "page": 5,
      "title_fa": "ساختار W-Frage",
      "explanation_fa": "در W-Frage اول کلمه پرسشی می‌آید، بعد فعل، بعد فاعل. دانش‌آموز باید این ترتیب را حفظ کند.",
      "examples": [
        {
          "audio_de": "A1_10_05",
          "de": "Woher kommst du?",
          "fa": "اهل کجایی؟"
        },
        {
          "audio_de": "A1_10_06",
          "de": "Wann beginnt der Kurs?",
          "fa": "کلاس کی شروع می‌شود؟"
        }
      ]
    },
    {
      "page": 6,
      "title_fa": "wie viel و wie viele",
      "explanation_fa": "اگر چیزی قابل شمارش نباشد (مثل آب، پول)، از wie viel استفاده می‌کنیم. اگر قابل شمارش باشد (مثل کتاب، سیب)، از wie viele استفاده می‌کنیم.",
      "examples": [
        {
          "audio_de": "A1_10_07",
          "de": "Wie viel Zeit hast du?",
          "fa": "چقدر وقت داری؟"
        },
        {
          "audio_de": "A1_10_08",
          "de": "Wie viele Bücher hast du?",
          "fa": "چند تا کتاب داری؟"
        }
      ]
    },
    {
      "page": 7,
      "title_fa": "جمع‌بندی معلمانه",
      "explanation_fa": "دو نوع سؤال داریم: سؤال بله/نه که فعل اول می‌آید، و سؤال با کلمه پرسشی که ترتیب آن: کلمه پرسشی + فعل + فاعل است. اگر این را بلد باشی، نصف مکالمه را برده‌ای."
    }
  ]
}
