{
  "id": "02_A1_konjugation_prasens",
  "title_de": "Ich komme, du kommst",
  "title_fa": "چرا فعل در آلمانی تغییر می‌کند؟",

  "vocabulary_before_lesson": [
    { "de": "kommen", "fa": "آمدن" },
    { "de": "wohnen", "fa": "زندگی کردن" },
    { "de": "arbeiten", "fa": "کار کردن" },
    { "de": "lernen", "fa": "یاد گرفتن" },

    { "de": "ich", "fa": "من" },
    { "de": "du", "fa": "تو" },
    { "de": "er", "fa": "او (مرد)" },
    { "de": "sie", "fa": "او (زن)" },
    { "de": "wir", "fa": "ما" },
    { "de": "ihr", "fa": "شماها" }
  ],

  "pages": [
    {
      "page": 1,
      "title_fa": "چرا فعل تغییر می‌کند؟",
      "explanation_fa": "در آلمانی آخر فعل تغییر می‌کند تا معلوم شود چه کسی کار را انجام می‌دهد. چون جای کلمات می‌تواند عوض شود، زبان آلمانی این اطلاعات را به آخر فعل می‌چسباند."
    },
    {
      "page": 2,
      "title_fa": "شکل اصلی فعل",
      "explanation_fa": "فعل‌ها در کتاب با -en نوشته می‌شوند. این شکل هنوز برای هیچ‌کس نیست.",
      "example": {
        "audio_de": "A1_02_01",
        "de": "kommen",
        "fa": "آمدن"
      }
    },
    {
      "page": 3,
      "title_fa": "ریشه فعل",
      "explanation_fa": "برای ساختن فعل، اول -en را حذف می‌کنیم. آنچه می‌ماند، ریشه فعل است.",
      "example": {
        "audio_de": "A1_02_02",
        "de": "kommen → komm",
        "fa": "ریشه فعل"
      }
    },
    {
      "page": 4,
      "title_fa": "علامت‌های آخر فعل",
      "explanation_fa": "به ریشه فعل، علامت‌هایی اضافه می‌کنیم تا فاعل مشخص شود.",
      "examples": [
        {
          "audio_de": "A1_02_03",
          "de": "Ich komme.",
          "fa": "من می‌آیم."
        },
        {
          "audio_de": "A1_02_04",
          "de": "Du kommst.",
          "fa": "تو می‌آیی."
        },
        {
          "audio_de": "A1_02_05",
          "de": "Er kommt.",
          "fa": "او می‌آید."
        }
      ]
    },
    {
      "page": 5,
      "title_fa": "چرا گاهی e اضافه می‌شود؟",
      "explanation_fa": "اگر تلفظ سخت باشد، زبان آلمانی برای راحتی دهان یک e اضافه می‌کند.",
      "examples": [
        {
          "audio_de": "A1_02_06",
          "de": "Du arbeitest.",
          "fa": "تو کار می‌کنی."
        },
        {
          "audio_de": "A1_02_07",
          "de": "Er arbeitet.",
          "fa": "او کار می‌کند."
        }
      ]
    }
  ]
}
